README.md
setup.py
search_engines/__init__.py
search_engines/ask_search.py
search_engines/bing_news.py
search_engines/bing_search.py
search_engines/dogpile_news.py
search_engines/dogpile_search.py
search_engines/google_news.py
search_engines/google_search.py
search_engines/utils.py
search_engines/yahoo_news.py
search_engines/yahoo_search.py
search_engines.egg-info/PKG-INFO
search_engines.egg-info/SOURCES.txt
search_engines.egg-info/dependency_links.txt
search_engines.egg-info/requires.txt
search_engines.egg-info/top_level.txt